aliyunsdkimageenhan/__init__.py
aliyunsdkimageenhan/endpoint.py
aliyunsdkimageenhan/request/__init__.py
aliyunsdkimageenhan/request/v20190930/AssessCompositionRequest.py
aliyunsdkimageenhan/request/v20190930/AssessExposureRequest.py
aliyunsdkimageenhan/request/v20190930/AssessSharpnessRequest.py
aliyunsdkimageenhan/request/v20190930/ChangeImageSizeRequest.py
aliyunsdkimageenhan/request/v20190930/ColorizeImageRequest.py
aliyunsdkimageenhan/request/v20190930/EnhanceImageColorRequest.py
aliyunsdkimageenhan/request/v20190930/ErasePersonRequest.py
aliyunsdkimageenhan/request/v20190930/ExtendImageStyleRequest.py
aliyunsdkimageenhan/request/v20190930/GenerateCartoonizedImageRequest.py
aliyunsdkimageenhan/request/v20190930/GenerateDynamicImageRequest.py
aliyunsdkimageenhan/request/v20190930/GenerateImageWithTextAndImageRequest.py
aliyunsdkimageenhan/request/v20190930/GenerateImageWithTextRequest.py
aliyunsdkimageenhan/request/v20190930/GenerateSuperResolutionImageRequest.py
aliyunsdkimageenhan/request/v20190930/GetAsyncJobResultRequest.py
aliyunsdkimageenhan/request/v20190930/ImageBlindCharacterWatermarkRequest.py
aliyunsdkimageenhan/request/v20190930/ImageBlindPicWatermarkRequest.py
aliyunsdkimageenhan/request/v20190930/ImitatePhotoStyleRequest.py
aliyunsdkimageenhan/request/v20190930/IntelligentCompositionRequest.py
aliyunsdkimageenhan/request/v20190930/MakeSuperResolutionImageRequest.py
aliyunsdkimageenhan/request/v20190930/RecolorHDImageRequest.py
aliyunsdkimageenhan/request/v20190930/RecolorImageRequest.py
aliyunsdkimageenhan/request/v20190930/RemoveImageSubtitlesRequest.py
aliyunsdkimageenhan/request/v20190930/RemoveImageWatermarkRequest.py
aliyunsdkimageenhan/request/v20190930/__init__.py
aliyun_python_sdk_imageenhan-1.1.12.dist-info/LICENSE
aliyun_python_sdk_imageenhan-1.1.12.dist-info/METADATA
aliyun_python_sdk_imageenhan-1.1.12.dist-info/WHEEL
aliyun_python_sdk_imageenhan-1.1.12.dist-info/top_level.txt
aliyun_python_sdk_imageenhan-1.1.12.dist-info/RECORD
